swiftascmaps/__init__.py
swiftascmaps/__version__.py
swiftascmaps/colors.py
swiftascmaps/make_cmap.py
swiftascmaps-1.6.0.dist-info/licenses/LICENSE.txt
swiftascmaps-1.6.0.dist-info/METADATA
swiftascmaps-1.6.0.dist-info/WHEEL
swiftascmaps-1.6.0.dist-info/top_level.txt
swiftascmaps-1.6.0.dist-info/RECORD
